biobb_remote/__init__.py
biobb_remote/slurm.py
biobb_remote/ssh_credentials.py
biobb_remote/ssh_session.py
biobb_remote/task.py
biobb_remote/conf/BSC_CTEP.json
biobb_remote/conf/BSC_MN4.json
biobb_remote/conf/BSC_Starlife.json
biobb_remote/conf/schema.json
biobb_remote/galaxy/get_hpc_credentials.xml
biobb_remote/notebook/biobb_MDsetup_adapter_tutorial.ipynb
biobb_remote/notebook/biobb_MDsetup_remote_nobiobb.ipynb
biobb_remote/notebook/biobb_MDsetup_remote_tutorial.ipynb
biobb_remote/notebook/biobb_remote_demo.ipynb
biobb_remote/scripts/__init__.py
biobb_remote/scripts/credentials.py
biobb_remote/scripts/scp_service.py
biobb_remote/scripts/slurm_test.py
biobb_remote/scripts/ssh_command.py
biobb_remote/test/environment.yml
biobb_remote-1.2.2.dist-info/LICENSE
biobb_remote-1.2.2.dist-info/METADATA
biobb_remote-1.2.2.dist-info/WHEEL
biobb_remote-1.2.2.dist-info/entry_points.txt
biobb_remote-1.2.2.dist-info/top_level.txt
biobb_remote-1.2.2.dist-info/RECORD
