Metadata-Version: 2.1
Name: biobb-remote
Version: 1.2.2
Summary: Biobb_remote is the Biobb module for remote execution via ssl.
Home-page: https://github.com/bioexcel/biobb_remote
Author: Biobb developers
Author-email: gelpi@ub.edu
License: UNKNOWN
Project-URL: Documentation, http://biobb_remote.readthedocs.io/en/latest/
Project-URL: Bioexcel, https://bioexcel.eu/
Keywords: Bioinformatics Workflows BioExcel Compatibility
Platform: UNKNOWN
Classifier: Development Status :: 3 - Alpha
Classifier: Programming Language :: Python :: 3
Classifier: License :: OSI Approved :: Apache Software License
Classifier: Operating System :: MacOS :: MacOS X
Classifier: Operating System :: POSIX
Requires-Python: >=3
Requires-Dist: paramiko (==2.7.2)
